Workbook

Sheet Instrucciones
A1: Carga de la Mercería — Lana Rosa
A2: Esta plantilla sirve para cargar en el ERP la mercancía de la tienda física (centro "Tienda/Mercería") antes de la apertura.
A3: IMPORTANTE: esta plantilla es SOLO para lo que se VENDE en la Mercería (el inventario de la TIENDA). Lo que usas para tejer (lanas, relleno, ojos… del inventario del TALLER) NO va aquí.
A4: Si dudas de un producto, pregúntate: ¿lo va a comprar una clienta en la tienda? Si sí, va aquí; si es para tejer, no.
A7: Cómo llenarla
A8: 1. Hoja "Productos": las primeras 34 filas son los productos que ya existen en el ERP. No cambies la columna ID.
A9: 2. Para cada producto que vas a tener en la tienda, escribe la cantidad comprada (ovillos o unidades) y el costo de compra de cada ovillo o unidad (lo que pagaste, con IVA).
A10: 3. Si un producto ya no lo vas a vender, escribe "No" en la columna "¿Se vende en la tienda?".
A11: 4. Los productos nuevos (agujas, herrajes, accesorios, relleno, tijeras, etc.) van en las filas vacías de abajo, sin ID.
A12: 5. Proveedor, factura y fecha de compra: llénalos si los tienes; sirven para el Kardex y para la contabilidad.
A13: 6. Código de barras: si el producto lo trae, escríbelo (o escanéalo con un lector); así se encuentra rápido en el POS.
A15: Columna "¿Cómo se vende?"
... A31: • Ejemplo de una aguja: Cantidad = 24, Costo por unidad = 1.800, "¿Cómo se vende?" = Por unidad.

Sheet Resumen
A1: Resumen de la carga (se calcula solo)
A3: Productos con cantidad comprada | B3: =COUNTIFS(Productos!K2:K150,">0")
A4: Ovillos o unidades compradas (suma) | B4: =SUM(Productos!K2:K150)
A5: Valor de la mercancía a costo (COP) | B5: =SUMPRODUCT(Productos!K2:K150,Productos!L2:L150)
A6: Productos nuevos (sin ID) por crear | B6: =COUNTIFS(Productos!A2:A150,"",Productos!C2:C150,"<>")
A7: Filas con algo por corregir | B7: =COUNTIF(Productos!T2:T150,"Falta*")
A8: Productos marcados "No se vende" | B8: =COUNTIF(Productos!J2:J150,"No")
A10: Si "Filas con algo por corregir" no es 0, revisa la columna T de la hoja Productos antes de enviar el archivo.

Sheet Productos
A1: ID (no tocar) | B1: Categoría | C1: Nombre del producto | D1: Marca | E1: Color / referencia | F1: Material | G1: Peso por unidad (g) | H1: Metros por unidad | I1: ¿Cómo se vende? | J1: ¿Se vende en la tienda? | K1: Cantidad comprada (ovillos o unidades) | L1: Costo de compra por ovillo o por unidad (COP) | M1: Proveedor | N1: N.º factura | O1: Fecha de compra | P1: Código de barras / SKU | Q1: Stock mínimo | R1: Precio de venta hoy (referencia) | S1: Notas | T1: Revisión (automática, no tocar)
A2: 00c81579-e842-41d6-a850-7eb1ebbd4117 | B2: Hilos | C2: Lana Happy Chenille - Marca DMC - Color Verde Limón Shade 29 - Presentación 15 gramos - 38 metros. (Chelin delgado) | D2: DMC | E2: Verde Limón | F2: Chenille | G2: 15 | H2: 38 | I2: Por ovillo y por gramo | J2: Sí | Q2: 0 | R2: $300 por gramo | T2: =IF(C2="","",IF(AND(K2<>"",L2=""),"Falta el costo",IF(AND(LEFT(I2,6)="Por ov",K2<>"",G2=""),"Falta el peso del ovillo",IF(AND(A2="",B2=""),"Falta la categoría",IF(AND(A2="",I2=""),"Falta cómo se vende",IF(AND(K2<>"",N2="",M2=""),"(opcional) sin proveedor","OK"))))))
A3: 3b2f47d0-0748-4827-981c-9d4df453b779 | B3: Lanas | C3: Lana Chelin - Marca Kusi Kusi - Color Almendra #2110 Lote 250428 - peso 160 gramos - 125 metros - 100% poliester | D3: Kusi Kusi | E3: Almendra | F3: Poliester | G3: 160 | H3: 125 | I3: Por ovillo y por gramo | J3: Sí | Q3: 0 | R3: $110 por gramo | T3: =IF(C3="","",IF(AND(K3<>"",L3=""),"Falta el costo",IF(AND(LEFT(I3,6)="Por ov",K3<>"",G3=""),"Falta el peso del ovillo",IF(AND(A3="",B3=""),"Falta la categoría",IF(AND(A3="",I3=""),"Falta cómo se vende",IF(AND(K3<>"",N3="",M3=""),"(opcional) sin proveedor","OK"))))))
A4: 6ba3a3ce-9781-4561-ad28-ff34c0a1e301 | B4: Lanas | C4: Lana Chelin - Marca Kusi Kusi - Color Amarillo #2103 Lote 250428 - peso 160 gramos - 125 metros - 100% poliester | D4: Kusi Kusi | E4: Amarillo | F4: Poliester | G4: 160 | H4: 125 | I4: Por ovillo y por gramo | J4: Sí | Q4: 0 | R4: $110 por unidad | T4: =IF(C4="","",IF(AND(K4<>"",L4=""),"Falta el costo",IF(AND(LEFT(I4,6)="Por ov",K4<>"",G4=""),"Falta el peso del ovillo",IF(AND(A4="",B4=""),"Falta la categoría",IF(AND(A4="",I4=""),"Falta cómo se vende",IF(AND(K4<>"",N4="",M4=""),"(opcional) sin proveedor","OK"))))))
A5: f8b7bdfe-aa92-477e-a335-a546812b696b | B5: Lanas | C5: Lana Chelin - Marca Kusi Kusi - Color Azul Rey #2112 Lote 250428 - peso 160 gramos - 125 metros - 100% poliester | D5: Kusi Kusi | E5: Azul Rey | F5: Poliester | G5: 160 | H5: 125 | I5: Por ovillo y por gramo | J5: Sí | Q5: 0 | R5: $110 por unidad | T5: =IF(C5="","",IF(AND(K5<>"",L5=""),"Falta el costo",IF(AND(LEFT(I5,6)="Por ov",K5<>"",G5=""),"Falta el peso del ovillo",IF(AND(A5="",B5=""),"Falta la categoría",IF(AND(A5="",I5=""),"Falta cómo se vende",IF(AND(K5<>"",N5="",M5=""),"(opcional) sin proveedor","OK"))))))
A6: a7cf2e30-4531-4b4f-be24-e4dcffda7a60 | B6: Lanas | C6: Lana Chelin - Marca Kusi Kusi - Color Blanco #2101 Lote 250428 - peso 160 gramos - 125 metros - 100% poliester | D6: Kusi Kusi | E6: Blanco | F6: Poliester | G6: 160 | H6: 125 | I6: Por ovillo y por gramo | J6: Sí | Q6: 0 | R6: $110 por gramo | T6: =IF(C6="","",IF(AND(K6<>"",L6=""),"Falta el costo",IF(AND(LEFT(I6,6)="Por ov",K6<>"",G6=""),"Falta el peso del ovillo",IF(AND(A6="",B6=""),"Falta la categoría",IF(AND(A6="",I6=""),"Falta cómo se vende",IF(AND(K6<>"",N6="",M6=""),"(opcional) sin proveedor","OK"))))))
A7: 538aa581-e759-483a-919e-3559190b4767 | B7: Lanas | C7: Lana Chelin - Marca Kusi Kusi - Color Crema #2108 Lote 250428 - peso 160 gramos - 125 metros - 100% poliester | D7: Kusi Kusi | E7: Crema | F7: Poliester | G7: 160 | H7: 125 | I7: Por ovillo y por gramo | J7: Sí | Q7: 0 | R7: $110 por unidad | T7: =IF(C7="","",IF(AND(K7<>"",L7=""),"Falta el costo",IF(AND(LEFT(I7,6)="Por ov",K7<>"",G7=""),"Falta el peso del ovillo",IF(AND(A7="",B7=""),"Falta la categoría",IF(AND(A7="",I7=""),"Falta cómo se vende",IF(AND(K7<>"",N7="",M7=""),"(opcional) sin proveedor","OK"))))))
A8: 6976d3ee-0bd4-4320-8574-93bc207dbf61 | B8: Lanas | C8: Lana Chelin - Marca Kusi Kusi - Color Gris Claro T18 Lote 250428 - peso 160 gramos - 125 metros - 100% poliester | D8: Kusi Kusi | E8: Gris Claro T18 | F8: Poliester | G8: 160 | H8: 125 | I8: Por ovillo y por gramo | J8: Sí | Q8: 0 | R8: $110 por gramo | T8: =IF(C8="","",IF(AND(K8<>"",L8=""),"Falta el costo",IF(AND(LEFT(I8,6)="Por ov",K8<>"",G8=""),"Falta el peso del ovillo",IF(AND(A8="",B8=""),"Falta la categoría",IF(AND(A8="",I8=""),"Falta cómo se vende",IF(AND(K8<>"",N8="",M8=""),"(opcional) sin proveedor","OK"))))))
A9: e6cf35a1-17cd-407d-b5a5-102ea4ce33f1 | B9: Lanas | C9: Lana Chelin - Marca Kusi Kusi - Color Gris Oscuro #2109 - peso 160 gramos - 125 metros - 100% poliester | D9: Kusi Kusi | E9: Gris Oscuro | F9: Poliester | G9: 160 | H9: 125 | I9: Por ovillo y por gramo | J9: Sí | Q9: 0 | R9: $110 por gramo | T9: =IF(C9="","",IF(AND(K9<>"",L9=""),"Falta el costo",IF(AND(LEFT(I9,6)="Por ov",K9<>"",G9=""),"Falta el peso del ovillo",IF(AND(A9="",B9=""),"Falta la categoría",IF(AND(A9="",I9=""),"Falta cómo se vende",IF(AND(K9<>"",N9="",M9=""),"(opcional) sin proveedor","OK"))))))
A10: bfce27d1-a2d1-493e-9934-c52292494593 | B10: Lanas | C10: Lana Chelin - Marca Kusi Kusi - Color Manzana #2106 Lote 250428 - peso 160 gramos - 125 metros - 100% poliester | D10: Kusi Kusi | E10: Manzana | F10: Poliester | G10: 160 | H10: 125 | I10: Por ovillo y por gramo | J10: Sí | Q10: 0 | R10: $110 por unidad | T10: =IF(C10="","",IF(AND(K10<>"",L10=""),"Falta el costo",IF(AND(LEFT(I10,6)="Por ov",K10<>"",G10=""),"Falta el peso del ovillo",IF(AND(A10="",B10=""),"Falta la categoría",IF(AND(A10="",I10=""),"Falta cómo se vende",IF(AND(K10<>"",N10="",M10=""),"(opcional) sin proveedor","OK"))))))
A11: 00f8df89-a56c-4db9-b420-d980f2ba085d | B11: Lanas | C11: Lana Chelin - Marca Kusi Kusi - Color Naranja T17 - peso 160 gramos - 125 metros - 100% poliester | D11: Kusi Kusi | E11: Naranja T17 | F11: Poliester | G11: 160 | H11: 125 | I11: Por ovillo y por gramo | J11: Sí | Q11: 0 | R11: $110 por gramo | T11: =IF(C11="","",IF(AND(K11<>"",L11=""),"Falta el costo",IF(AND(LEFT(I11,6)="Por ov",K11<>"",G11=""),"Falta el peso del ovillo",IF(AND(A11="",B11=""),"Falta la categoría",IF(AND(A11="",I11=""),"Falta cómo se vende",IF(AND(K11<>"",N11="",M11=""),"(opcional) sin proveedor","OK"))))))
A12: 33ca3b30-94bc-4d34-9748-327dfdaa819c | B12: Lanas | C12: Lana Chelin - Marca Kusi Kusi - Color Piel #2170 Lote 250608 - peso 160 gramos - 125 metros - 100% poliester | D12: Kusi Kusi | E12: Piel | F12: Poliester | G12: 160 | H12: 125 | I12: Por ovillo y por gramo | J12: Sí | Q12: 0 | R12: $110 por unidad | T12: =IF(C12="","",IF(AND(K12<>"",L12=""),"Falta el costo",IF(AND(LEFT(I12,6)="Por ov",K12<>"",G12=""),"Falta el peso del ovillo",IF(AND(A12="",B12=""),"Falta la categoría",IF(AND(A12="",I12=""),"Falta cómo se vende",IF(AND(K12<>"",N12="",M12=""),"(opcional) sin proveedor","OK"))))))
A13: b56ff83b-274f-491d-8a8d-4a860d21a35c | B13: Lanas | C13: Lana Chelin - Marca Kusi Kusi - Color Rosado Claro #T22 Lote 250608 - peso 160 gramos - 125 metros - 100% poliester | D13: Kusi Kusi | E13: Rosado Claro | F13: Poliester | G13: 160 | H13: 125 | I13: Por ovillo y por gramo | J13: Sí | Q13: 0 | R13: $110 por unidad | T13: =IF(C13="","",IF(AND(K13<>"",L13=""),"Falta el costo",IF(AND(LEFT(I13,6)="Por ov",K13<>"",G13=""),"Falta el peso del ovillo",IF(AND(A13="",B13=""),"Falta la categoría",IF(AND(A13="",I13=""),"Falta cómo se vende",IF(AND(K13<>"",N13="",M13=""),"(opcional) sin proveedor","OK"))))))
... A35: 7bf0ca4b-53da-438c-9a67-8112f9a8d1b8 | B35: Lanas | C35: Lana Polar - Marca Kusi Kusi - Color Blanco 03 Lote 250628 - Peso 100 gramos - 55 metros - 100% poliester | D35: Kusi Kusi | E35: Blanco 03 | F35: Poliester | G35: 100 | H35: 55 | I35: Por ovillo y por gramo | J35: Sí | Q35: 0 | R35: $130 por gramo | T35: =IF(C35="","",IF(AND(K35<>"",L35=""),"Falta el costo",IF(AND(LEFT(I35,6)="Por ov",K35<>"",G35=""),"Falta el peso del ovillo",IF(AND(A35="",B35=""),"Falta la categoría",IF(AND(A35="",I35=""),"Falta cómo se vende",IF(AND(K35<>"",N35="",M35=""),"(opcional) sin proveedor","OK"))))))
T36: =IF(C36="","",IF(AND(K36<>"",L36=""),"Falta el costo",IF(AND(LEFT(I36,6)="Por ov",K36<>"",G36=""),"Falta el peso del ovillo",IF(AND(A36="",B36=""),"Falta la categoría",IF(AND(A36="",I36=""),"Falta cómo se vende",IF(AND(K36<>"",N36="",M36=""),"(opcional) sin proveedor","OK"))))))
T37: =IF(C37="","",IF(AND(K37<>"",L37=""),"Falta el costo",IF(AND(LEFT(I37,6)="Por ov",K37<>"",G37=""),"Falta el peso del ovillo",IF(AND(A37="",B37=""),"Falta la categoría",IF(AND(A37="",I37=""),"Falta cómo se vende",IF(AND(K37<>"",N37="",M37=""),"(opcional) sin proveedor","OK"))))))
T38: =IF(C38="","",IF(AND(K38<>"",L38=""),"Falta el costo",IF(AND(LEFT(I38,6)="Por ov",K38<>"",G38=""),"Falta el peso del ovillo",IF(AND(A38="",B38=""),"Falta la categoría",IF(AND(A38="",I38=""),"Falta cómo se vende",IF(AND(K38<>"",N38="",M38=""),"(opcional) sin proveedor","OK"))))))
T39: =IF(C39="","",IF(AND(K39<>"",L39=""),"Falta el costo",IF(AND(LEFT(I39,6)="Por ov",K39<>"",G39=""),"Falta el peso del ovillo",IF(AND(A39="",B39=""),"Falta la categoría",IF(AND(A39="",I39=""),"Falta cómo se vende",IF(AND(K39<>"",N39="",M39=""),"(opcional) sin proveedor","OK"))))))
T40: =IF(C40="","",IF(AND(K40<>"",L40=""),"Falta el costo",IF(AND(LEFT(I40,6)="Por ov",K40<>"",G40=""),"Falta el peso del ovillo",IF(AND(A40="",B40=""),"Falta la categoría",IF(AND(A40="",I40=""),"Falta cómo se vende",IF(AND(K40<>"",N40="",M40=""),"(opcional) sin proveedor","OK"))))))
T41: =IF(C41="","",IF(AND(K41<>"",L41=""),"Falta el costo",IF(AND(LEFT(I41,6)="Por ov",K41<>"",G41=""),"Falta el peso del ovillo",IF(AND(A41="",B41=""),"Falta la categoría",IF(AND(A41="",I41=""),"Falta cómo se vende",IF(AND(K41<>"",N41="",M41=""),"(opcional) sin proveedor","OK"))))))
T42: =IF(C42="","",IF(AND(K42<>"",L42=""),"Falta el costo",IF(AND(LEFT(I42,6)="Por ov",K42<>"",G42=""),"Falta el peso del ovillo",IF(AND(A42="",B42=""),"Falta la categoría",IF(AND(A42="",I42=""),"Falta cómo se vende",IF(AND(K42<>"",N42="",M42=""),"(opcional) sin proveedor","OK"))))))
T43: =IF(C43="","",IF(AND(K43<>"",L43=""),"Falta el costo",IF(AND(LEFT(I43,6)="Por ov",K43<>"",G43=""),"Falta el peso del ovillo",IF(AND(A43="",B43=""),"Falta la categoría",IF(AND(A43="",I43=""),"Falta cómo se vende",IF(AND(K43<>"",N43="",M43=""),"(opcional) sin proveedor","OK"))))))
T44: =IF(C44="","",IF(AND(K44<>"",L44=""),"Falta el costo",IF(AND(LEFT(I44,6)="Por ov",K44<>"",G44=""),"Falta el peso del ovillo",IF(AND(A44="",B44=""),"Falta la categoría",IF(AND(A44="",I44=""),"Falta cómo se vende",IF(AND(K44<>"",N44="",M44=""),"(opcional) sin proveedor","OK"))))))
T45: =IF(C45="","",IF(AND(K45<>"",L45=""),"Falta el costo",IF(AND(LEFT(I45,6)="Por ov",K45<>"",G45=""),"Falta el peso del ovillo",IF(AND(A45="",B45=""),"Falta la categoría",IF(AND(A45="",I45=""),"Falta cómo se vende",IF(AND(K45<>"",N45="",M45=""),"(opcional) sin proveedor","OK"))))))
T46: =IF(C46="","",IF(AND(K46<>"",L46=""),"Falta el costo",IF(AND(LEFT(I46,6)="Por ov",K46<>"",G46=""),"Falta el peso del ovillo",IF(AND(A46="",B46=""),"Falta la categoría",IF(AND(A46="",I46=""),"Falta cómo se vende",IF(AND(K46<>"",N46="",M46=""),"(opcional) sin proveedor","OK"))))))
T47: =IF(C47="","",IF(AND(K47<>"",L47=""),"Falta el costo",IF(AND(LEFT(I47,6)="Por ov",K47<>"",G47=""),"Falta el peso del ovillo",IF(AND(A47="",B47=""),"Falta la categoría",IF(AND(A47="",I47=""),"Falta cómo se vende",IF(AND(K47<>"",N47="",M47=""),"(opcional) sin proveedor","OK"))))))
... T150: =IF(C150="","",IF(AND(K150<>"",L150=""),"Falta el costo",IF(AND(LEFT(I150,6)="Por ov",K150<>"",G150=""),"Falta el peso del ovillo",IF(AND(A150="",B150=""),"Falta la categoría",IF(AND(A150="",I150=""),"Falta cómo se vende",IF(AND(K150<>"",N150="",M150=""),"(opcional) sin proveedor","OK"))))))

Sheet Listas
A1: Lanas | B1: Bombay | C1: Por ovillo y por gramo | D1: Sí
A2: Hilos | B2: Mega Import | C2: Por unidad | D2: No
A3: Agujas | B3: Otros
A4: Herrajes | B4: (nuevo proveedor: escríbelo en Notas)
A5: Accesorios y herramientas
A6: Relleno
A7: Tijeras
A8: Alfileres
A9: Kits de tejido
A10: Otros
